cliquet/__init__.py
cliquet/authentication.py
cliquet/authorization.py
cliquet/errors.py
cliquet/events.py
cliquet/initialization.py
cliquet/logs.py
cliquet/schema.py
cliquet/statsd.py
cliquet/utils.py
cliquet/cache/__init__.py
cliquet/cache/memory.py
cliquet/cache/redis.py
cliquet/cache/postgresql/__init__.py
cliquet/cache/postgresql/schema.sql
cliquet/listeners/__init__.py
cliquet/listeners/redis.py
cliquet/permission/__init__.py
cliquet/permission/memory.py
cliquet/permission/redis.py
cliquet/permission/postgresql/__init__.py
cliquet/permission/postgresql/schema.sql
cliquet/resource/__init__.py
cliquet/resource/model.py
cliquet/resource/schema.py
cliquet/resource/viewset.py
cliquet/scripts/__init__.py
cliquet/scripts/cliquet.py
cliquet/storage/__init__.py
cliquet/storage/exceptions.py
cliquet/storage/generators.py
cliquet/storage/memory.py
cliquet/storage/redis.py
cliquet/storage/postgresql/__init__.py
cliquet/storage/postgresql/client.py
cliquet/storage/postgresql/pool.py
cliquet/storage/postgresql/schema.sql
cliquet/storage/postgresql/migrations/migration_001_002.sql
cliquet/storage/postgresql/migrations/migration_002_003.sql
cliquet/storage/postgresql/migrations/migration_003_004.sql
cliquet/storage/postgresql/migrations/migration_004_005.sql
cliquet/storage/postgresql/migrations/migration_005_006.sql
cliquet/storage/postgresql/migrations/migration_006_007.sql
cliquet/storage/postgresql/migrations/migration_007_008.sql
cliquet/storage/postgresql/migrations/migration_008_009.sql
cliquet/storage/postgresql/migrations/migration_009_010.sql
cliquet/storage/postgresql/migrations/migration_010_011.sql
cliquet/tests/__init__.py
cliquet/tests/support.py
cliquet/tests/test_authentication.py
cliquet/tests/test_authorization.py
cliquet/tests/test_cache.py
cliquet/tests/test_deprecation.py
cliquet/tests/test_errors.py
cliquet/tests/test_initialization.py
cliquet/tests/test_listeners.py
cliquet/tests/test_logging.py
cliquet-3.1.5.dist-info/DESCRIPTION.rst
cliquet-3.1.5.dist-info/METADATA
cliquet-3.1.5.dist-info/RECORD
cliquet-3.1.5.dist-info/WHEEL
cliquet-3.1.5.dist-info/entry_points.txt
cliquet-3.1.5.dist-info/metadata.json
cliquet-3.1.5.dist-info/top_level.txt
