Metadata-Version: 2.0
Name: cliquet
Version: 3.1.5
Summary: Micro service API toolkit
Home-page: https://github.com/mozilla-services/cliquet
Author: Mozilla Services
Author-email: services-dev@mozilla.com
License: Apache License (2.0)
Keywords: web services
Platform: UNKNOWN
Classifier: Programming Language :: Python
Classifier: Programming Language :: Python :: 2.7
Classifier: Programming Language :: Python :: 3.4
Classifier: Programming Language :: Python :: 3.5
Classifier: Programming Language :: Python :: Implementation :: CPython
Classifier: Programming Language :: Python :: Implementation :: PyPy
Classifier: Topic :: Internet :: WWW/HTTP
Classifier: Topic :: Internet :: WWW/HTTP :: WSGI :: Application
Classifier: License :: OSI Approved :: Apache Software License
Requires-Dist: colander
Requires-Dist: colorama
Requires-Dist: cornice (>=1.1)
Requires-Dist: enum34
Requires-Dist: pyramid-multiauth (>=0.8)
Requires-Dist: pyramid-tm
Requires-Dist: python-dateutil
Requires-Dist: redis
Requires-Dist: requests
Requires-Dist: six
Requires-Dist: structlog
Requires-Dist: ujson (>=1.35)
Provides-Extra: monitoring
Requires-Dist: newrelic; extra == 'monitoring'
Requires-Dist: raven; extra == 'monitoring'
Requires-Dist: statsd; extra == 'monitoring'
Requires-Dist: werkzeug; extra == 'monitoring'
Provides-Extra: postgresql
Requires-Dist: SQLAlchemy; extra == 'postgresql'
Requires-Dist: psycopg2 (>2.5); extra == 'postgresql'
Requires-Dist: zope.sqlalchemy; extra == 'postgresql'
